docko/__init__.py
docko/boltz.py
docko/chai.py
docko/diffdock.py
docko/docko.py
docko/helpers.py
docko/main.py
docko/vina.py
docko-0.1.3.data/data/LICENSE
docko-0.1.3.dist-info/LICENSE
docko-0.1.3.dist-info/METADATA
docko-0.1.3.dist-info/WHEEL
docko-0.1.3.dist-info/entry_points.txt
docko-0.1.3.dist-info/top_level.txt
docko-0.1.3.dist-info/RECORD
