Metadata-Version: 2.2
Name: docko
Version: 0.1.3
Home-page: https://github.com/arianemora/docko/
Author: Ariane Mora
Author-email: ariane.n.mora@gmail.com
License: GPL3
Project-URL: Bug Tracker, https://github.com/arianemora/docko/
Project-URL: Documentation, https://github.com/arianemora/docko/
Project-URL: Source Code, https://github.com/arianemora/docko/
Keywords: docking,protein-engineering
Classifier: Intended Audience :: Science/Research
Classifier: License :: OSI Approved :: GNU General Public License v3 (GPLv3)
Classifier: Natural Language :: English
Classifier: Operating System :: OS Independent
Classifier: Programming Language :: Python :: 3.6
Classifier: Programming Language :: Python :: 3.7
Classifier: Programming Language :: Python :: 3.8
Classifier: Topic :: Scientific/Engineering :: Bio-Informatics
Requires-Python: >=3.8
License-File: LICENSE
Requires-Dist: babel==2.16.0
Requires-Dist: biopython
Requires-Dist: h5py
Requires-Dist: jupyterlab
Requires-Dist: matplotlib
Requires-Dist: networkx
Requires-Dist: numpy
Requires-Dist: opencv-python
Requires-Dist: OpenMM==8.1.1
Requires-Dist: pandas
Requires-Dist: primer3-py==2.0.3
Requires-Dist: prompt_toolkit==3.0.47
Requires-Dist: protobuf==5.28.1
Requires-Dist: pysam==0.22.1
Requires-Dist: pytz==2024.1
Requires-Dist: PyYAML==6.0.2
Requires-Dist: pyzmq==26.2.0
Requires-Dist: rdkit
Requires-Dist: regex==2024.9.11
Requires-Dist: scikit-learn
Requires-Dist: sciutil==1.0.3
Requires-Dist: sciviso==1.0.9
Requires-Dist: seaborn==0.13.2
Requires-Dist: statannot==0.2.3
Requires-Dist: statsmodels==0.14.2
Requires-Dist: tqdm==4.66.5
Requires-Dist: sciutil
Requires-Dist: boltz>=2.0.0
Dynamic: author
Dynamic: author-email
Dynamic: classifier
Dynamic: description
Dynamic: description-content-type
Dynamic: home-page
Dynamic: keywords
Dynamic: license
Dynamic: project-url
Dynamic: requires-dist
Dynamic: requires-python
